wisepaasdatahubedgesdk/EdgeAgent.py
wisepaasdatahubedgesdk/__init__.py
wisepaasdatahubedgesdk/Common/Constants.py
wisepaasdatahubedgesdk/Common/Converter.py
wisepaasdatahubedgesdk/Common/DataRecoverHelper.py
wisepaasdatahubedgesdk/Common/Logger.py
wisepaasdatahubedgesdk/Common/Topic.py
wisepaasdatahubedgesdk/Common/Utils.py
wisepaasdatahubedgesdk/Common/__init__.py
wisepaasdatahubedgesdk/Model/Edge.py
wisepaasdatahubedgesdk/Model/Event.py
wisepaasdatahubedgesdk/Model/MQTTMessage.py
wisepaasdatahubedgesdk/Model/__init__.py
WISE_PaaS_DataHub_Edge_Python_SDK-1.1.7.dist-info/METADATA
WISE_PaaS_DataHub_Edge_Python_SDK-1.1.7.dist-info/WHEEL
WISE_PaaS_DataHub_Edge_Python_SDK-1.1.7.dist-info/top_level.txt
WISE_PaaS_DataHub_Edge_Python_SDK-1.1.7.dist-info/RECORD
