Metadata-Version: 2.1
Name: WISE_PaaS_DataHub_Edge_Python_SDK
Version: 1.1.7
Summary: WISEPaaS_DataHub_Edge_Python_SDK package allows developers to write Python applications which access the WISE-PaaS/DataHub Platform via MQTT or MQTT over the secure webSocket protocol.
Home-page: https://github.com/advwacloud/WISEPaaS.DataHub.Edge.Python.SDK
Author: Steven Li
Author-email: StevenHY.Li@advantech.com.tw
License: UNKNOWN
Platform: UNKNOWN
Classifier: Programming Language :: Python :: 3
